Metadata-Version: 1.0
Name: pyckstart
Version: 0.0.3
Summary: Module for easy python modules creation
Home-page: UNKNOWN
Author: Zulko 2013, Jc Saad-Dupuy 2014
Author-email: UNKNOWN
License: LICENSE.txt
Keywords: python module template engine setuptools
Platform: UNKNOWN
